deepagent_lab/__init__.py
deepagent_lab/_version.py
deepagent_lab/agent.py
deepagent_lab/agent_wrapper.py
deepagent_lab/config.py
deepagent_lab/handlers.py
deepagent_lab/langgraph_utils.py
deepagent_lab/launcher.py
deepagent_lab/labextension/package.json
deepagent_lab/labextension/schemas/deepagent-lab/package.json.orig
deepagent_lab/labextension/static/3.ff03cc29c0c31cceeac5.js
deepagent_lab/labextension/static/3.ff03cc29c0c31cceeac5.js.LICENSE.txt
deepagent_lab/labextension/static/344.7313cb80ed03f869bca2.js
deepagent_lab/labextension/static/38.9e3742a066c929b49df5.js
deepagent_lab/labextension/static/38.9e3742a066c929b49df5.js.LICENSE.txt
deepagent_lab/labextension/static/728.8a0c99a67f7bb4943970.js
deepagent_lab/labextension/static/remoteEntry.8c531800cd2e4d9d2af5.js
deepagent_lab/labextension/static/style.js
deepagent_lab/labextension/static/third-party-licenses.json
deepagent_lab-0.1.4.data/data/etc/jupyter/jupyter_server_config.d/deepagent_lab.json
deepagent_lab-0.1.4.data/data/share/jupyter/labextensions/deepagent-lab/package.json
deepagent_lab-0.1.4.data/data/share/jupyter/labextensions/deepagent-lab/schemas/deepagent-lab/package.json.orig
deepagent_lab-0.1.4.data/data/share/jupyter/labextensions/deepagent-lab/static/3.ff03cc29c0c31cceeac5.js
deepagent_lab-0.1.4.data/data/share/jupyter/labextensions/deepagent-lab/static/3.ff03cc29c0c31cceeac5.js.LICENSE.txt
deepagent_lab-0.1.4.data/data/share/jupyter/labextensions/deepagent-lab/static/344.7313cb80ed03f869bca2.js
deepagent_lab-0.1.4.data/data/share/jupyter/labextensions/deepagent-lab/static/38.9e3742a066c929b49df5.js
deepagent_lab-0.1.4.data/data/share/jupyter/labextensions/deepagent-lab/static/38.9e3742a066c929b49df5.js.LICENSE.txt
deepagent_lab-0.1.4.data/data/share/jupyter/labextensions/deepagent-lab/static/728.8a0c99a67f7bb4943970.js
deepagent_lab-0.1.4.data/data/share/jupyter/labextensions/deepagent-lab/static/remoteEntry.8c531800cd2e4d9d2af5.js
deepagent_lab-0.1.4.dist-info/METADATA
deepagent_lab-0.1.4.dist-info/WHEEL
deepagent_lab-0.1.4.dist-info/entry_points.txt
deepagent_lab-0.1.4.dist-info/licenses/LICENSE
deepagent_lab-0.1.4.dist-info/RECORD
