Metadata-Version: 2.4
Name: deepagent-lab
Version: 0.1.4
Dynamic: Keywords
Summary: JupyterLab extension with chat interface for DeepAgents
Project-URL: Homepage, https://github.com/dkedar7/deepagent-lab
Project-URL: Bug Tracker, https://github.com/dkedar7/deepagent-lab/issues
Project-URL: Repository, https://github.com/dkedar7/deepagent-lab.git
Author: Kedar Dabhadkar
License: MIT License
License-File: LICENSE
Classifier: Framework :: Jupyter
Classifier: Framework :: Jupyter :: JupyterLab
Classifier: Framework :: Jupyter :: JupyterLab :: 4
Classifier: Framework :: Jupyter :: JupyterLab :: Extensions
Classifier: Framework :: Jupyter :: JupyterLab :: Extensions :: Prebuilt
Classifier: License :: OSI Approved :: MIT License
Classifier: Programming Language :: Python
Classifier: Programming Language :: Python :: 3
Classifier: Programming Language :: Python :: 3.8
Classifier: Programming Language :: Python :: 3.9
Classifier: Programming Language :: Python :: 3.10
Classifier: Programming Language :: Python :: 3.11
Requires-Python: >=3.11
Requires-Dist: deepagents>=0.1.0
Requires-Dist: jupyter-server<3,>=2.0.1
Requires-Dist: langgraph>=0.0.1
Requires-Dist: python-dotenv>=0.19.0
Provides-Extra: dev
Requires-Dist: jupyter-server[test]<3,>=2.0.1; extra == 'dev'
